MANIFEST.in
setup.py
paths/__init__.py
paths/config.py
paths/metadata.py
paths/path.py
paths/system.py
paths.egg-info/PKG-INFO
paths.egg-info/SOURCES.txt
paths.egg-info/dependency_links.txt
paths.egg-info/not-zip-safe
paths.egg-info/top_level.txt