Metadata-Version: 1.1
Name: paths
Version: 0.0.1a1
Summary: Python utility module for dealing with local paths
Home-page: http://github.com/nikcub/paths
Author: Nik Cubrilovic
Author-email: nikcub@gmail.com
License: UNKNOWN
Download-URL: http://github.com/nikcub/paths
Platform: UNKNOWN
Classifier: Development Status :: 3 - Alpha
Classifier: Environment :: Console
Classifier: Intended Audience :: Developers
Classifier: License :: OSI Approved :: MIT License
Classifier: Natural Language :: English
Classifier: Operating System :: OS Independent
Classifier: Programming Language :: Python :: 2.6
Classifier: Programming Language :: Python :: 2.7
Classifier: Programming Language :: Python :: 3.3
Classifier: Programming Language :: Python :: Implementation :: PyPy
Classifier: Topic :: System :: Installation/Setup
Classifier: Topic :: System :: Software Distribution
